<?xml version="1.0" encoding="UTF-8"?>
<Mpeg7 xmlns="urn:mpeg:mpeg7:schema:2001" 
xmlns:xsi="http://www.w3.org/2001/XMLSchema-instance" 
xmlns:mpeg7="urn:mpeg:mpeg7:schema:2001" 
xsi:schemaLocation="urn:mpeg:mpeg7:schema:2001 Mpeg7-2001.xsd">
    <DescriptionUnit xsi:type="MelodyType">
       <Meter>
          <Numerator>3</Numerator>
          <Denominator>4</Denominator>
       </Meter>
       <Scale>1 2 3 4 5 6 7 8 9 10 11 12</Scale>
       <Key>
          <KeyNote display="so">G</KeyNote>
       </Key>
       <MelodySequence>
          <StartingNote>
             <StartingFrequency>293.66</StartingFrequency>
             <StartingPitch accidental="natural" height="4">
                <PitchNote display="re">D</PitchNote>
             </StartingPitch>
          </StartingNote>
          <NoteArray>
             <Note>
                <Interval>2.0</Interval>
                <NoteRelDuration>0.767299</NoteRelDuration>
             </Note>
             <Note>
                <Interval>3.0</Interval>
                <NoteRelDuration>-1.9327</NoteRelDuration>
             </Note>
             <Note>
                <Interval>4.0</Interval>
                <NoteRelDuration>1.30835</NoteRelDuration>
             </Note>
             <Note>
                <Interval>0.0</Interval>
                <NoteRelDuration>1.01625</NoteRelDuration>
             </Note>
             <Note>
                <Interval>0.0</Interval>
                <NoteRelDuration>-0.981272</NoteRelDuration>
             </Note>
             <Note>
                <Interval>-2.0</Interval>
                <NoteRelDuration>-0.116166</NoteRelDuration>
             </Note>
             <Note>
                <Interval>-2.0</Interval>
                <NoteRelDuration>0.028519</NoteRelDuration>
             </Note>
             <Note>
                <Interval>2.0</Interval>
                <NoteRelDuration>0.047221</NoteRelDuration>
             </Note>
             <Note>
                <Interval>-2.0</Interval>
                <NoteRelDuration>-0.930661</NoteRelDuration>
             </Note>
             <Note>
                <Interval>-3.0</Interval>
                <NoteRelDuration>1.53916</NoteRelDuration>
             </Note>
             <Note>
                <Interval>-2.0</Interval>
                <NoteRelDuration>-0.72509</NoteRelDuration>
             </Note>
             <Note>
                <Interval>2.0</Interval>
                <NoteRelDuration>0.810316</NoteRelDuration>
             </Note>
             <Note>
                <Interval>3.0</Interval>
                <NoteRelDuration>-1.96349</NoteRelDuration>
             </Note>
             <Note>
                <Interval>4.0</Interval>
                <NoteRelDuration>1.26161</NoteRelDuration>
             </Note>
             <Note>
                <Interval>0.0</Interval>
                <NoteRelDuration>0.941037</NoteRelDuration>
             </Note>
             <Note>
                <Interval>0.0</Interval>
                <NoteRelDuration>-0.960693</NoteRelDuration>
             </Note>
             <Note>
                <Interval>-2.0</Interval>
                <NoteRelDuration>-0.0250869</NoteRelDuration>
             </Note>
             <Note>
                <Interval>-2.0</Interval>
                <NoteRelDuration>-0.00272211</NoteRelDuration>
             </Note>
             <Note>
                <Interval>2.0</Interval>
                <NoteRelDuration>0.00842498</NoteRelDuration>
             </Note>
             <Note>
                <Interval>-2.0</Interval>
                <NoteRelDuration>-0.069402</NoteRelDuration>
             </Note>
             <Note>
                <Interval>-3.0</Interval>
                <NoteRelDuration>0.791547</NoteRelDuration>
             </Note>
             <Note>
                <Interval>-2.0</Interval>
                <NoteRelDuration>-1.78842</NoteRelDuration>
             </Note>
             <Note>
                <Interval>2.0</Interval>
                <NoteRelDuration>1.66159</NoteRelDuration>
             </Note>
             <Note>
                <Interval>5.0</Interval>
                <NoteRelDuration>-1.62683</NoteRelDuration>
             </Note>
             <Note>
                <Interval>-2.0</Interval>
                <NoteRelDuration>1.05117</NoteRelDuration>
             </Note>
             <Note>
                <Interval>-5.0</Interval>
                <NoteRelDuration>3.13985</NoteRelDuration>
             </Note>
             <Note>
                <Interval>5.0</Interval>
                <NoteRelDuration>-3.12866</NoteRelDuration>
             </Note>
             <Note>
                <Interval>-3.0</Interval>
                <NoteRelDuration>0.649637</NoteRelDuration>
             </Note>
             <Note>
                <Interval>-2.0</Interval>
                <NoteRelDuration>-1.75872</NoteRelDuration>
             </Note>
             <Note>
                <Interval>-3.0</Interval>
                <NoteRelDuration>0.0467271</NoteRelDuration>
             </Note>
             <Note>
                <Interval>5.0</Interval>
                <NoteRelDuration>2.0691</NoteRelDuration>
             </Note>
             <Note>
                <Interval>3.0</Interval>
                <NoteRelDuration>-2.1459</NoteRelDuration>
             </Note>
             <Note>
                <Interval>4.0</Interval>
                <NoteRelDuration>1.11101</NoteRelDuration>
             </Note>
             <Note>
                <Interval>-2.0</Interval>
                <NoteRelDuration>-0.145013</NoteRelDuration>
             </Note>
             <Note>
                <Interval>-2.0</Interval>
                <NoteRelDuration>0.0904346</NoteRelDuration>
             </Note>
             <Note>
                <Interval>-3.0</Interval>
                <NoteRelDuration>1.65738</NoteRelDuration>
             </Note>
             <Note>
                <Interval>3.0</Interval>
                <NoteRelDuration>-1.62543</NoteRelDuration>
             </Note>
             <Note>
                <Interval>-1.0</Interval>
                <NoteRelDuration>-0.113139</NoteRelDuration>
             </Note>
             <Note>
                <Interval>-2.0</Interval>
                <NoteRelDuration>0.158312</NoteRelDuration>
             </Note>
             <Note>
                <Interval>-2.0</Interval>
                <NoteRelDuration>-1.00025</NoteRelDuration>
             </Note>
             <Note>
                <Interval>-2.0</Interval>
                <NoteRelDuration>1.93055</NoteRelDuration>
             </Note>
             <Note>
                <Interval>2.0</Interval>
                <NoteRelDuration>-2.10715</NoteRelDuration>
             </Note>
             <Note>
                <Interval>5.0</Interval>
                <NoteRelDuration>1.1347</NoteRelDuration>
             </Note>
             <Note>
                <Interval>-3.0</Interval>
                <NoteRelDuration>0.0252807</NoteRelDuration>
             </Note>
             <Note>
                <Interval>-2.0</Interval>
                <NoteRelDuration>-0.037129</NoteRelDuration>
             </Note>
             <Note>
                <Interval>0.0</Interval>
                <NoteRelDuration>1.56884</NoteRelDuration>
             </Note>
             <Note>
                <Interval>5.0</Interval>
                <NoteRelDuration>-1.58022</NoteRelDuration>
             </Note>
             <Note>
                <Interval>-3.0</Interval>
                <NoteRelDuration>0.639024</NoteRelDuration>
             </Note>
             <Note>
                <Interval>-2.0</Interval>
                <NoteRelDuration>-1.76322</NoteRelDuration>
             </Note>
             <Note>
                <Interval>-3.0</Interval>
                <NoteRelDuration>0.150424</NoteRelDuration>
             </Note>
             <Note>
                <Interval>3.0</Interval>
                <NoteRelDuration>2.00533</NoteRelDuration>
             </Note>
             <Note>
                <Interval>5.0</Interval>
                <NoteRelDuration>-2.02295</NoteRelDuration>
             </Note>
             <Note>
                <Interval>4.0</Interval>
                <NoteRelDuration>0.991394</NoteRelDuration>
             </Note>
             <Note>
                <Interval>-2.0</Interval>
                <NoteRelDuration>-0.0145627</NoteRelDuration>
             </Note>
             <Note>
                <Interval>-2.0</Interval>
                <NoteRelDuration>0.0660214</NoteRelDuration>
             </Note>
             <Note>
                <Interval>2.0</Interval>
                <NoteRelDuration>0.582005</NoteRelDuration>
             </Note>
             <Note>
                <Interval>2.0</Interval>
                <NoteRelDuration>-1.71988</NoteRelDuration>
             </Note>
             <Note>
                <Interval>1.0</Interval>
                <NoteRelDuration>0.205894</NoteRelDuration>
             </Note>
             <Note>
                <Interval>-1.0</Interval>
                <NoteRelDuration>1.8</NoteRelDuration>
             </Note>
             <Note>
                <Interval>-2.0</Interval>
                <NoteRelDuration>-2.06323</NoteRelDuration>
             </Note>
             <Note>
                <Interval>-2.0</Interval>
                <NoteRelDuration>0.316105</NoteRelDuration>
             </Note>
             <Note>
                <Interval>-3.0</Interval>
                <NoteRelDuration>1.41937</NoteRelDuration>
             </Note>
             <Note>
                <Interval>-2.0</Interval>
                <NoteRelDuration>0.0474661</NoteRelDuration>
             </Note>
             <Note>
                <Interval>0.0</Interval>
                <NoteRelDuration>-1.66591</NoteRelDuration>
             </Note>
             <Note>
                <Interval>2.0</Interval>
                <NoteRelDuration>1.62821</NoteRelDuration>
             </Note>
             <Note>
                <Interval>5.0</Interval>
                <NoteRelDuration>-1.58129</NoteRelDuration>
             </Note>
             <Note>
                <Interval>-7.0</Interval>
                <NoteRelDuration>0.953361</NoteRelDuration>
             </Note>
             <Note>
                <Interval>0.0</Interval>
                <NoteRelDuration>2.66693</NoteRelDuration>
             </Note>
             <Note>
                <Interval>2.0</Interval>
                <NoteRelDuration>-1.90409</NoteRelDuration>
             </Note>
             <Note>
                <Interval>3.0</Interval>
                <NoteRelDuration>-1.90562</NoteRelDuration>
             </Note>
             <Note>
                <Interval>4.0</Interval>
                <NoteRelDuration>1.12507</NoteRelDuration>
             </Note>
             <Note>
                <Interval>0.0</Interval>
                <NoteRelDuration>1.07298</NoteRelDuration>
             </Note>
             <Note>
                <Interval>0.0</Interval>
                <NoteRelDuration>-1.04058</NoteRelDuration>
             </Note>
             <Note>
                <Interval>-2.0</Interval>
                <NoteRelDuration>0.0602533</NoteRelDuration>
             </Note>
             <Note>
                <Interval>-2.0</Interval>
                <NoteRelDuration>-0.0897801</NoteRelDuration>
             </Note>
             <Note>
                <Interval>2.0</Interval>
                <NoteRelDuration>0.0983786</NoteRelDuration>
             </Note>
             <Note>
                <Interval>-2.0</Interval>
                <NoteRelDuration>-1.0086</NoteRelDuration>
             </Note>
             <Note>
                <Interval>-3.0</Interval>
                <NoteRelDuration>1.56434</NoteRelDuration>
             </Note>
             <Note>
                <Interval>-2.0</Interval>
                <NoteRelDuration>-0.627415</NoteRelDuration>
             </Note>
             <Note>
                <Interval>2.0</Interval>
                <NoteRelDuration>0.731619</NoteRelDuration>
             </Note>
             <Note>
                <Interval>3.0</Interval>
                <NoteRelDuration>-1.91285</NoteRelDuration>
             </Note>
             <Note>
                <Interval>4.0</Interval>
                <NoteRelDuration>1.21903</NoteRelDuration>
             </Note>
             <Note>
                <Interval>0.0</Interval>
                <NoteRelDuration>0.951903</NoteRelDuration>
             </Note>
             <Note>
                <Interval>0.0</Interval>
                <NoteRelDuration>-1.04652</NoteRelDuration>
             </Note>
             <Note>
                <Interval>-2.0</Interval>
                <NoteRelDuration>0.0449549</NoteRelDuration>
             </Note>
             <Note>
                <Interval>-2.0</Interval>
                <NoteRelDuration>0.0118825</NoteRelDuration>
             </Note>
             <Note>
                <Interval>2.0</Interval>
                <NoteRelDuration>0.0289799</NoteRelDuration>
             </Note>
             <Note>
                <Interval>-2.0</Interval>
                <NoteRelDuration>-0.116604</NoteRelDuration>
             </Note>
             <Note>
                <Interval>-3.0</Interval>
                <NoteRelDuration>0.732055</NoteRelDuration>
             </Note>
             <Note>
                <Interval>-2.0</Interval>
                <NoteRelDuration>-1.63853</NoteRelDuration>
             </Note>
             <Note>
                <Interval>2.0</Interval>
                <NoteRelDuration>1.60038</NoteRelDuration>
             </Note>
             <Note>
                <Interval>5.0</Interval>
                <NoteRelDuration>-1.64829</NoteRelDuration>
             </Note>
             <Note>
                <Interval>-2.0</Interval>
                <NoteRelDuration>0.988389</NoteRelDuration>
             </Note>
             <Note>
                <Interval>0.0</Interval>
                <NoteRelDuration>2.65072</NoteRelDuration>
             </Note>
             <Note>
                <Interval>2.0</Interval>
                <NoteRelDuration>-1.87417</NoteRelDuration>
             </Note>
             <Note>
                <Interval>3.0</Interval>
                <NoteRelDuration>-1.91764</NoteRelDuration>
             </Note>
             <Note>
                <Interval>4.0</Interval>
                <NoteRelDuration>1.17714</NoteRelDuration>
             </Note>
             <Note>
                <Interval>0.0</Interval>
                <NoteRelDuration>1.03351</NoteRelDuration>
             </Note>
             <Note>
                <Interval>0.0</Interval>
                <NoteRelDuration>-1.03952</NoteRelDuration>
             </Note>
             <Note>
                <Interval>-2.0</Interval>
                <NoteRelDuration>0.0381317</NoteRelDuration>
             </Note>
             <Note>
                <Interval>-2.0</Interval>
                <NoteRelDuration>-0.092928</NoteRelDuration>
             </Note>
             <Note>
                <Interval>2.0</Interval>
                <NoteRelDuration>0.0636324</NoteRelDuration>
             </Note>
             <Note>
                <Interval>-2.0</Interval>
                <NoteRelDuration>-1.00879</NoteRelDuration>
             </Note>
             <Note>
                <Interval>-3.0</Interval>
                <NoteRelDuration>1.62202</NoteRelDuration>
             </Note>
             <Note>
                <Interval>-2.0</Interval>
                <NoteRelDuration>-0.586715</NoteRelDuration>
             </Note>
             <Note>
                <Interval>2.0</Interval>
                <NoteRelDuration>0.728788</NoteRelDuration>
             </Note>
             <Note>
                <Interval>3.0</Interval>
                <NoteRelDuration>-1.92176</NoteRelDuration>
             </Note>
             <Note>
                <Interval>4.0</Interval>
                <NoteRelDuration>1.11819</NoteRelDuration>
             </Note>
             <Note>
                <Interval>0.0</Interval>
                <NoteRelDuration>1.09212</NoteRelDuration>
             </Note>
             <Note>
                <Interval>0.0</Interval>
                <NoteRelDuration>-1.05583</NoteRelDuration>
             </Note>
             <Note>
                <Interval>-2.0</Interval>
                <NoteRelDuration>-0.0178754</NoteRelDuration>
             </Note>
             <Note>
                <Interval>-2.0</Interval>
                <NoteRelDuration>0.0793589</NoteRelDuration>
             </Note>
             <Note>
                <Interval>2.0</Interval>
                <NoteRelDuration>-0.0260848</NoteRelDuration>
             </Note>
             <Note>
                <Interval>-2.0</Interval>
                <NoteRelDuration>-1.11223</NoteRelDuration>
             </Note>
             <Note>
                <Interval>-3.0</Interval>
                <NoteRelDuration>1.76285</NoteRelDuration>
             </Note>
             <Note>
                <Interval>-2.0</Interval>
                <NoteRelDuration>-0.70711</NoteRelDuration>
             </Note>
             <Note>
                <Interval>2.0</Interval>
                <NoteRelDuration>0.770742</NoteRelDuration>
             </Note>
             <Note>
                <Interval>5.0</Interval>
                <NoteRelDuration>-1.77072</NoteRelDuration>
             </Note>
             <Note>
                <Interval>-2.0</Interval>
                <NoteRelDuration>1.02992</NoteRelDuration>
             </Note>
             <Note>
                <Interval>-5.0</Interval>
                <NoteRelDuration>3.17994</NoteRelDuration>
             </Note>
             <Note>
                <Interval>5.0</Interval>
                <NoteRelDuration>-3.11856</NoteRelDuration>
             </Note>
             <Note>
                <Interval>-3.0</Interval>
                <NoteRelDuration>0.650469</NoteRelDuration>
             </Note>
             <Note>
                <Interval>-2.0</Interval>
                <NoteRelDuration>-1.88163</NoteRelDuration>
             </Note>
             <Note>
                <Interval>-3.0</Interval>
                <NoteRelDuration>0.338011</NoteRelDuration>
             </Note>
             <Note>
                <Interval>3.0</Interval>
                <NoteRelDuration>1.917</NoteRelDuration>
             </Note>
             <Note>
                <Interval>5.0</Interval>
                <NoteRelDuration>-2.24862</NoteRelDuration>
             </Note>
             <Note>
                <Interval>4.0</Interval>
                <NoteRelDuration>1.16338</NoteRelDuration>
             </Note>
             <Note>
                <Interval>-2.0</Interval>
                <NoteRelDuration>-0.0510346</NoteRelDuration>
             </Note>
             <Note>
                <Interval>-2.0</Interval>
                <NoteRelDuration>0.148841</NoteRelDuration>
             </Note>
             <Note>
                <Interval>-3.0</Interval>
                <NoteRelDuration>1.43798</NoteRelDuration>
             </Note>
             <Note>
                <Interval>3.0</Interval>
                <NoteRelDuration>-1.54176</NoteRelDuration>
             </Note>
             <Note>
                <Interval>-1.0</Interval>
                <NoteRelDuration>0.017902</NoteRelDuration>
             </Note>
             <Note>
                <Interval>-2.0</Interval>
                <NoteRelDuration>-0.0506292</NoteRelDuration>
             </Note>
             <Note>
                <Interval>-2.0</Interval>
                <NoteRelDuration>-0.0188396</NoteRelDuration>
             </Note>
             <Note>
                <Interval>-2.0</Interval>
                <NoteRelDuration>0.0985668</NoteRelDuration>
             </Note>
             <Note>
                <Interval>2.0</Interval>
                <NoteRelDuration>-0.142239</NoteRelDuration>
             </Note>
             <Note>
                <Interval>5.0</Interval>
                <NoteRelDuration>0.0560649</NoteRelDuration>
             </Note>
             <Note>
                <Interval>-3.0</Interval>
                <NoteRelDuration>0.0719867</NoteRelDuration>
             </Note>
             <Note>
                <Interval>-2.0</Interval>
                <NoteRelDuration>0.045691</NoteRelDuration>
             </Note>
             <Note>
                <Interval>0.0</Interval>
                <NoteRelDuration>1.54001</NoteRelDuration>
             </Note>
             <Note>
                <Interval>5.0</Interval>
                <NoteRelDuration>-1.58598</NoteRelDuration>
             </Note>
             <Note>
                <Interval>-3.0</Interval>
                <NoteRelDuration>0.0233144</NoteRelDuration>
             </Note>
             <Note>
                <Interval>-2.0</Interval>
                <NoteRelDuration>-0.0604419</NoteRelDuration>
             </Note>
             <Note>
                <Interval>-3.0</Interval>
                <NoteRelDuration>-0.0541428</NoteRelDuration>
             </Note>
             <Note>
                <Interval>3.0</Interval>
                <NoteRelDuration>0.0979793</NoteRelDuration>
             </Note>
             <Note>
                <Interval>5.0</Interval>
                <NoteRelDuration>-0.0568181</NoteRelDuration>
             </Note>
             <Note>
                <Interval>4.0</Interval>
                <NoteRelDuration>0.0595778</NoteRelDuration>
             </Note>
             <Note>
                <Interval>-2.0</Interval>
                <NoteRelDuration>-0.189854</NoteRelDuration>
             </Note>
             <Note>
                <Interval>-2.0</Interval>
                <NoteRelDuration>0.173088</NoteRelDuration>
             </Note>
             <Note>
                <Interval>2.0</Interval>
                <NoteRelDuration>-0.147956</NoteRelDuration>
             </Note>
             <Note>
                <Interval>2.0</Interval>
                <NoteRelDuration>0.113805</NoteRelDuration>
             </Note>
             <Note>
                <Interval>1.0</Interval>
                <NoteRelDuration>0.0397617</NoteRelDuration>
             </Note>
             <Note>
                <Interval>-1.0</Interval>
                <NoteRelDuration>0.660463</NoteRelDuration>
             </Note>
             <Note>
                <Interval>-2.0</Interval>
                <NoteRelDuration>-1.76803</NoteRelDuration>
             </Note>
             <Note>
                <Interval>-2.0</Interval>
                <NoteRelDuration>1.03577</NoteRelDuration>
             </Note>
             <Note>
                <Interval>-3.0</Interval>
                <NoteRelDuration>-0.0207472</NoteRelDuration>
             </Note>
             <Note>
                <Interval>-2.0</Interval>
                <NoteRelDuration>0.733374</NoteRelDuration>
             </Note>
             <Note>
                <Interval>0.0</Interval>
                <NoteRelDuration>-1.59941</NoteRelDuration>
             </Note>
             <Note>
                <Interval>2.0</Interval>
                <NoteRelDuration>1.55193</NoteRelDuration>
             </Note>
             <Note>
                <Interval>5.0</Interval>
                <NoteRelDuration>-1.68293</NoteRelDuration>
             </Note>
             <Note>
                <Interval>-2.0</Interval>
                <NoteRelDuration>1.08397</NoteRelDuration>
             </Note>
          </NoteArray>
       </MelodySequence>
    </DescriptionUnit>
</Mpeg7>
